{
  "response_code": 0,
  "results": [
    {
      "type": "multiple",
      "difficulty": "hard",
      "category": "Entertainment: Music",
      "question": "Chino Moreno is the lead singer of which alternative metal band?",
      "correct_answer": "Deftones",
      "incorrect_answers": ["Tool", "Korn", "Type O Negative"]
    },
    {
      "type": "boolean",
      "difficulty": "medium",
      "category": "Sports",
      "question": "The Olympics tennis court is a giant green screen.",
      "correct_answer": "True",
      "incorrect_answers": ["False"]
    },
    {
      "type": "multiple",
      "difficulty": "easy",
      "category": "History",
      "question": "Which famous world leader is famed for the saying, &quot;Let them eat cake&quot;, yet is rumored that he/she never said it at all?",
      "correct_answer": "Marie Antoinette",
      "incorrect_answers": ["Czar Nicholas II", "Elizabeth I", "Henry VIII"]
    },
    {
      "type": "multiple",
      "difficulty": "medium",
      "category": "Entertainment: Music",
      "question": "Which European capital city gives its name to a 1981 song by Ultravox?",
      "correct_answer": "Vienna",
      "incorrect_answers": ["Berlin", "Paris", "Brussels"]
    },
    {
      "type": "boolean",
      "difficulty": "hard",
      "category": "Art",
      "question": "The Statue of Liberty&#039;s official name is &ldquo;Liberty Enlightening the World&rdquo;.",
      "correct_answer": "True",
      "incorrect_answers": ["False"]
    },
    {
      "type": "multiple",
      "difficulty": "medium",
      "category": "Sports",
      "question": "With which team did Michael Schumacher make his Formula One debut at the 1991 Belgian Grand Prix?",
      "correct_answer": "Jordan",
      "incorrect_answers": ["Benetton", "Ferrari", "Mercedes"]
    },
    {
      "type": "multiple",
      "difficulty": "easy",
      "category": "Geography",
      "question": "How many time zones does China have?",
      "correct_answer": "1",
      "incorrect_answers": ["3", "4", "2"]
    },
    {
      "type": "multiple",
      "difficulty": "hard",
      "category": "General Knowledge",
      "question": "The Swedish word &quot;Grunka&quot; means what in English?",
      "correct_answer": "Thing",
      "incorrect_answers": ["People", "Place", "Pineapple"]
    },
    {
      "type": "multiple",
      "difficulty": "easy",
      "category": "Entertainment: Television",
      "question": "Which character was played by Dustin Diamond in the sitcom &#039;Saved by the Bell&#039;?",
      "correct_answer": "Screech",
      "incorrect_answers": ["Zack", "Mr. Belding", "A.C. Slater"]
    },
    {
      "type": "multiple",
      "difficulty": "hard",
      "category": "Animals",
      "question": "What was the name of the Ethiopian Wolf before they knew it was related to wolves?",
      "correct_answer": "Simien Jackel",
      "incorrect_answers": [
        "Ethiopian Coyote",
        "Amharic Fox",
        "Canis Simiensis"
      ]
    }
  ]
}
